src/data_mem.v
// data_mem.v
module data_mem #(
    parameter ADDR_WIDTH = 10,    
    parameter DATA_WIDTH = 32
) (
    input  wire                   clk,
    input  wire                   MemRead,
    input  wire                   MemWrite,
    input  wire [ADDR_WIDTH-1:0]  addr,
    input  wire [DATA_WIDTH-1:0]  write_data,
    output reg  [DATA_WIDTH-1:0]  read_data
);

    reg [DATA_WIDTH-1:0] mem [0:(1<<ADDR_WIDTH)-1];

    always @(posedge clk) begin
        if (MemWrite)
            mem[addr] <= write_data;
    end

    always @(*) begin
        if (MemRead)
            read_data = mem[addr];
        else
            read_data = 32'd0;
    end

endmodule

tb/data_mem/data_mem_tb.v
// data_mem_tb.v
`timescale 1ns/1ps

module data_mem_tb;
    reg         clk;
    reg         MemRead, MemWrite;
    reg  [9:0]  addr;
    reg  [31:0] write_data;
    wire [31:0] read_data;

    data_mem #(.ADDR_WIDTH(10), .DATA_WIDTH(32)) uut (
        .clk        (clk),
        .MemRead    (MemRead),
        .MemWrite   (MemWrite),
        .addr       (addr),
        .write_data (write_data),
        .read_data  (read_data)
    );

    initial begin
        $dumpfile("data_mem_tb.vcd");
        $dumpvars(0, data_mem_tb);
        clk = 0;
        MemRead = 0; MemWrite = 0;
        addr = 0; write_data = 0;

        // 1) Escreve 123 em endereço 5
        #5; addr = 10'd5; write_data = 32'd123; MemWrite = 1;
        #10; MemWrite = 0;

        // 2) Lê do endereço 5
        #5; addr = 10'd5; MemRead = 1;
        #5; $display("read_data @5 = %0d", read_data);

        // 3) Lê de um endereço não escrito
        #5; addr = 10'd10; MemRead = 1;
        #5; $display("read_data @10 = %0d", read_data);

        // 4) Testa Overwrite: escreve 77 em 5 e lê
        #5; addr = 10'd5; write_data = 32'd77; MemWrite = 1; MemRead = 0;
        #10; MemWrite = 0;
        #5; addr = 10'd5; MemRead = 1;
        #5; $display("read_data @5 = %0d", read_data);

        #10 $finish;
    end
    
    always #5 clk = ~clk;
endmodule

tb/data_mem/data_mem_tb.vcd
$date
	Sun Jun 08 20:54:49 2025
$end
$version
	Icarus Verilog
$end
$timescale
	1ps
$end
$scope module data_mem_tb $end
$var wire 32 ! read_data [31:0] $end
$var reg 1 " MemRead $end
$var reg 1 # MemWrite $end
$var reg 10 $ addr [9:0] $end
$var reg 1 % clk $end
$var reg 32 & write_data [31:0] $end
$scope module uut $end
$var wire 1 " MemRead $end
$var wire 1 # MemWrite $end
$var wire 10 ' addr [9:0] $end
$var wire 1 % clk $end
$var wire 32 ( write_data [31:0] $end
$var reg 32 ) read_data [31:0] $end
$upscope $end
$upscope $end
$enddefinitions $end
#0
$dumpvars
b0 )
b0 (
b0 '
b0 &
0%
b0 $
0#
0"
b0 !
$end
#5000
1%
1#
b1111011 &
b1111011 (
b101 $
b101 '
#10000
0%
#15000
1%
0#
#20000
b1111011 !
b1111011 )
0%
1"
#25000
1%
#30000
bx !
bx )
0%
b1010 $
b1010 '
#35000
1%
#40000
b0 !
b0 )
0%
0"
1#
b1001101 &
b1001101 (
b101 $
b101 '
#45000
1%
#50000
0%
0#
#55000
b1001101 !
b1001101 )
1%
1"
