src/control.v
module control (
    input  wire [6:0] opcode,    
    input  wire [2:0] funct3,     
    input  wire       funct7_5, 
    output reg        RegWrite,  
    output reg        MemRead,   
    output reg        MemWrite,  
    output reg        Branch,     
    output reg        ALUSrc,    
    output reg        MemToReg,  
    output reg [1:0]  ALUControl 
);

    always @(*) begin
        // Defaults (nenhuma ação)
        RegWrite   = 1'b0;
        MemRead    = 1'b0;
        MemWrite   = 1'b0;
        Branch     = 1'b0;
        ALUSrc     = 1'b0;
        MemToReg   = 1'b0;
        ALUControl = 2'b00;

        case (opcode)
            7'b0000011: begin  // lw
                RegWrite   = 1;
                MemRead    = 1;
                ALUSrc     = 1;
                MemToReg   = 1;
                // ALUControl = ADD (address calc)
                ALUControl = 2'b00;
            end
            7'b0100011: begin  // sw
                MemWrite   = 1;
                ALUSrc     = 1;
                // ALUControl = ADD (address calc)
                ALUControl = 2'b00;
            end
            7'b1100011: begin  // beq
                Branch     = 1;
                ALUSrc     = 0;
                // ALUControl = SUB (compare)
                ALUControl = 2'b01;
            end
            7'b0110011: begin  // R-type (add, sub, and, or)
                RegWrite = 1;
                ALUSrc   = 0;
                case ({funct7_5, funct3})
                    4'b0000: ALUControl = 2'b00; // ADD  (funct7_5=0, funct3=000)
                    4'b1000: ALUControl = 2'b01; // SUB  (funct7_5=1, funct3=000)
                    4'b0111: ALUControl = 2'b10; // AND  (funct7_5=0, funct3=111)
                    4'b0110: ALUControl = 2'b11; // OR   (funct7_5=0, funct3=110)
                    default: ALUControl = 2'b00;
                endcase
            end
            7'b0010011: begin  // addi
                RegWrite = 1;
                ALUSrc   = 1;
                // ALUControl = ADD (immediate)
                ALUControl = 2'b00;
            end
        endcase
    end
endmodule

tb/datapath/control_tb.v
// control_tb.v
`timescale 1ns/1ps

module control_tb;
    reg  [6:0] opcode;
    reg  [2:0] funct3;
    reg        funct7_5;
    wire       RegWrite, MemRead, MemWrite, Branch, ALUSrc, MemToReg;
    wire [1:0] ALUControl;

    control uut (
        .opcode     (opcode),
        .funct3     (funct3),
        .funct7_5   (funct7_5),
        .RegWrite   (RegWrite),
        .MemRead    (MemRead),
        .MemWrite   (MemWrite),
        .Branch     (Branch),
        .ALUSrc     (ALUSrc),
        .MemToReg   (MemToReg),
        .ALUControl (ALUControl)
    );

    initial begin
        $dumpfile("control_tb.vcd");
        $dumpvars(0, control_tb);

        // Teste lw
        opcode   = 7'b0000011; funct3 = 3'b010; funct7_5 = 1'b0; #10;
        $display("lw -> RegWrite=%b, MemRead=%b, ALUSrc=%b, MemToReg=%b, ALUControl=%b",
                 RegWrite, MemRead, ALUSrc, MemToReg, ALUControl);

        // Teste sw
        opcode   = 7'b0100011; funct3 = 3'b010; funct7_5 = 1'b0; #10;
        $display("sw -> MemWrite=%b, ALUSrc=%b, ALUControl=%b",
                 MemWrite, ALUSrc, ALUControl);

        // Teste beq
        opcode   = 7'b1100011; funct3 = 3'b000; funct7_5 = 1'b0; #10;
        $display("beq -> Branch=%b, ALUSrc=%b, ALUControl=%b",
                 Branch, ALUSrc, ALUControl);

        // Teste add 
        opcode   = 7'b0110011; funct3 = 3'b000; funct7_5 = 1'b0; #10;
        $display("add -> RegWrite=%b, ALUSrc=%b, ALUControl=%b",
                 RegWrite, ALUSrc, ALUControl);

        // Test sub 
        opcode   = 7'b0110011; funct3 = 3'b000; funct7_5 = 1'b1; #10;
        $display("sub -> RegWrite=%b, ALUSrc=%b, ALUControl=%b",
                 RegWrite, ALUSrc, ALUControl);

        // Test and 
        opcode   = 7'b0110011; funct3 = 3'b111; funct7_5 = 1'b0; #10;
        $display("and -> ALUControl=%b", ALUControl);

        // Test or 
        opcode   = 7'b0110011; funct3 = 3'b110; funct7_5 = 1'b0; #10;
        $display("or  -> ALUControl=%b", ALUControl);

        // Test addi
        opcode   = 7'b0010011; funct3 = 3'b000; funct7_5 = 1'b0; #10;
        $display("addi -> RegWrite=%b, ALUSrc=%b, ALUControl=%b",
                 RegWrite, ALUSrc, ALUControl);

        #10 $finish;
    end
endmodule

tb/control/control_tb.vcd
$date
	Sun Jun 08 20:52:45 2025
$end
$version
	Icarus Verilog
$end
$timescale
	1ps
$end
$scope module control_tb $end
$var wire 1 ! RegWrite $end
$var wire 1 " MemWrite $end
$var wire 1 # MemToReg $end
$var wire 1 $ MemRead $end
$var wire 1 % Branch $end
$var wire 1 & ALUSrc $end
$var wire 2 ' ALUControl [1:0] $end
$var reg 3 ( funct3 [2:0] $end
$var reg 1 ) funct7_5 $end
$var reg 7 * opcode [6:0] $end
$scope module uut $end
$var wire 3 + funct3 [2:0] $end
$var wire 1 ) funct7_5 $end
$var wire 7 , opcode [6:0] $end
$var reg 2 - ALUControl [1:0] $end
$var reg 1 & ALUSrc $end
$var reg 1 % Branch $end
$var reg 1 $ MemRead $end
$var reg 1 # MemToReg $end
$var reg 1 " MemWrite $end
$var reg 1 ! RegWrite $end
$upscope $end
$upscope $end
$enddefinitions $end
#0
$dumpvars
b0 -
b11 ,
b10 +
b11 *
0)
b10 (
b0 '
1&
0%
1$
1#
0"
1!
$end
#10000
1"
0#
1&
0$
0!
b100011 *
b100011 ,
#20000
b1 '
b1 -
1%
0&
0"
b0 (
b0 +
b1100011 *
b1100011 ,
#30000
1!
b0 '
b0 -
0%
b110011 *
b110011 ,
#40000
b1 '
b1 -
1!
1)
#50000
b10 '
b10 -
1!
0)
b111 (
b111 +
#60000
b11 '
b11 -
1!
b110 (
b110 +
#70000
1&
b0 '
b0 -
1!
b0 (
b0 +
b10011 *
b10011 ,
