tb/datapath/pc_mux.v
module pc_mux (
    input  wire [31:0] pc_plus4,    
    input  wire [31:0] branch_target, 
    input  wire        sel,           
    output reg  [31:0] pc_next       
);

    always @(*) begin
        if (sel)
            pc_next = branch_target;
        else
            pc_next = pc_plus4;
    end

endmodule

src/data_mem.v
// data_mem.v
module data_mem #(
    parameter ADDR_WIDTH = 10,    
    parameter DATA_WIDTH = 32
) (
    input  wire                   clk,
    input  wire                   MemRead,
    input  wire                   MemWrite,
    input  wire [ADDR_WIDTH-1:0]  addr,
    input  wire [DATA_WIDTH-1:0]  write_data,
    output reg  [DATA_WIDTH-1:0]  read_data
);

    reg [DATA_WIDTH-1:0] mem [0:(1<<ADDR_WIDTH)-1];

    always @(posedge clk) begin
        if (MemWrite)
            mem[addr] <= write_data;
    end

    always @(*) begin
        if (MemRead)
            read_data = mem[addr];
        else
            read_data = 32'd0;
    end

endmodule

tb/datapath/ula.v
module ula (
    input  wire [31:0] op_a,       
    input  wire [31:0] op_b,      
    input  wire [1:0] control,     
//      control = 2'b00 → ADD
//                2'b01 → SUB
//                2'b10 → AND
//                2'b11 → OR
    output reg  [31:0] result,     
    output wire        zero        
);


    always @(*) begin
        case (control)
            2'b00: result = op_a + op_b;  // ADD
            2'b01: result = op_a - op_b;  // SUB
            2'b10: result = op_a & op_b;  // AND
            2'b11: result = op_a | op_b;  // OR
            default: result = 32'b0;
        endcase
    end

    assign zero = (result == 32'b0);

endmodule

src/alu_src_mux.v
module alu_src_mux (
    input  wire [31:0] reg_data2,  
    input  wire [31:0] imm_ext,    
    input  wire        sel,        
    output reg  [31:0] alu_in2     
);

    always @(*) begin
        if (sel)
            alu_in2 = imm_ext;
        else
            alu_in2 = reg_data2;
    end
endmodule

tb/imm_gen/imm_gen.v
module imm_gen (
    input  wire [31:0] instr, 
    input  wire [1:0]  sel,    
    output reg  [31:0] imm_out 
);

    wire [11:0] imm_i = instr[31:20];                
    wire [11:0] imm_s = {instr[31:25], instr[11:7]}; 
    wire [12:0] imm_b = {instr[31], instr[7],
                        instr[30:25], instr[11:8], 1'b0}; 

    always @(*) begin
        case (sel)
            2'b00: 
                imm_out = {{20{imm_i[11]}}, imm_i};
            2'b01: 
                imm_out = {{20{imm_s[11]}}, imm_s};
            2'b10: 
                imm_out = {{19{imm_b[12]}}, imm_b};
            default:
                imm_out = 32'd0;
        endcase
    end

endmodule

tb/datapath/regfile.v
// regfile.v
module regfile (
    input  wire        clk,       
    input  wire        RegWrite,   
    input  wire [4:0]  rs1,        
    input  wire [4:0]  rs2,        
    input  wire [4:0]  rd,        
    input  wire [31:0] write_data, 
    output wire [31:0] read_data1,
    output wire [31:0] read_data2  
);

    reg [31:0] regs [0:31];

    assign read_data1 = (rs1 == 5'd0) ? 32'd0 : regs[rs1];
    assign read_data2 = (rs2 == 5'd0) ? 32'd0 : regs[rs2];

    always @(posedge clk) begin
        if (RegWrite && (rd != 5'd0)) begin
            regs[rd] <= write_data;
        end
    end

    // (Opcional) inicializa todos em zero na simulação
    integer i;
    initial begin
        for (i = 0; i < 32; i = i + 1) regs[i] = 32'd0;
    end

endmodule

src/control.v
module control (
    input  wire [6:0] opcode,    
    input  wire [2:0] funct3,     
    input  wire       funct7_5, 
    output reg        RegWrite,  
    output reg        MemRead,   
    output reg        MemWrite,  
    output reg        Branch,     
    output reg        ALUSrc,    
    output reg        MemToReg,  
    output reg [1:0]  ALUControl 
);

    always @(*) begin
        // Defaults (nenhuma ação)
        RegWrite   = 1'b0;
        MemRead    = 1'b0;
        MemWrite   = 1'b0;
        Branch     = 1'b0;
        ALUSrc     = 1'b0;
        MemToReg   = 1'b0;
        ALUControl = 2'b00;

        case (opcode)
            7'b0000011: begin  // lw
                RegWrite   = 1;
                MemRead    = 1;
                ALUSrc     = 1;
                MemToReg   = 1;
                // ALUControl = ADD (address calc)
                ALUControl = 2'b00;
            end
            7'b0100011: begin  // sw
                MemWrite   = 1;
                ALUSrc     = 1;
                // ALUControl = ADD (address calc)
                ALUControl = 2'b00;
            end
            7'b1100011: begin  // beq
                Branch     = 1;
                ALUSrc     = 0;
                // ALUControl = SUB (compare)
                ALUControl = 2'b01;
            end
            7'b0110011: begin  // R-type (add, sub, and, or)
                RegWrite = 1;
                ALUSrc   = 0;
                case ({funct7_5, funct3})
                    4'b0000: ALUControl = 2'b00; // ADD  (funct7_5=0, funct3=000)
                    4'b1000: ALUControl = 2'b01; // SUB  (funct7_5=1, funct3=000)
                    4'b0111: ALUControl = 2'b10; // AND  (funct7_5=0, funct3=111)
                    4'b0110: ALUControl = 2'b11; // OR   (funct7_5=0, funct3=110)
                    default: ALUControl = 2'b00;
                endcase
            end
            7'b0010011: begin  // addi
                RegWrite = 1;
                ALUSrc   = 1;
                // ALUControl = ADD (immediate)
                ALUControl = 2'b00;
            end
        endcase
    end
endmodule

src/inst_mem.v
module inst_mem #(
    parameter ADDR_WIDTH = 8,            
    parameter DATA_WIDTH = 32,             
    parameter MEM_FILE   = "instructions.mem"
) (
    input  wire [ADDR_WIDTH-1:0] addr,      
    output reg  [DATA_WIDTH-1:0] instr     
);

    // 256 palavras de 32 bits
    reg [DATA_WIDTH-1:0] mem[0 : (1<<ADDR_WIDTH)-1];

    // carrega o programa no início da simulação
    initial begin
        $readmemh(MEM_FILE, mem);
    end

    // leitura combinacional
    always @(*) begin
        instr = mem[addr];
    end

endmodule

tb/datapath/datapath.v
module data_path (
    input  wire        clk,
    input  wire        rst,      
    output wire [31:0] pc_out     
);

    // PC  
    reg [31:0] PC;
    wire [31:0] pc_plus4 = PC + 32'd4;
    wire [31:0] pc_branch;     
    wire [31:0] next_pc;

    // Fetch 
    wire [31:0] instr;
    inst_mem #(.MEM_FILE("instructions.mem")) IM (
        .addr  (PC[7:0]),
        .instr (instr)
    );

    // Decode  
    wire [6:0] opcode = instr[6:0];
    wire [4:0] rs1    = instr[19:15];
    wire [4:0] rs2    = instr[24:20];
    wire [4:0] rd     = instr[11:7];
    wire [2:0] funct3 = instr[14:12];
    wire       funct7_5 = instr[30];

    // Sinais de controle
    wire RegWrite, MemRead, MemWrite, Branch, ALUSrc, MemToReg;
    wire [1:0] ALUControl;
    control CU (
        .opcode     (opcode),
        .funct3     (funct3),
        .funct7_5   (funct7_5),
        .RegWrite   (RegWrite),
        .MemRead    (MemRead),
        .MemWrite   (MemWrite),
        .Branch     (Branch),
        .ALUSrc     (ALUSrc),
        .MemToReg   (MemToReg),
        .ALUControl (ALUControl)
    );

    // Register File 
    wire [31:0] reg_rd1, reg_rd2;
    regfile RF (
        .clk        (clk),
        .RegWrite   (RegWrite),
        .rs1        (rs1),
        .rs2        (rs2),
        .rd         (rd),
        .write_data ( (MemToReg) ? data_rd : alu_res ),
        .read_data1 (reg_rd1),
        .read_data2 (reg_rd2)
    );

    // ImmGen 
    wire [31:0] imm_ext;
    wire [1:0]  imm_sel = (opcode==7'b0100011) ? 2'b01 :   
                          (opcode==7'b1100011) ? 2'b10 :   
                                                  2'b00;    
    imm_gen IG (
        .instr   (instr),
        .sel     (imm_sel),
        .imm_out (imm_ext)
    );

    // ALU  
    wire [31:0] alu_in2, alu_res;
    wire        zero;
    alu_src_mux M1 (
        .reg_data2(reg_rd2),
        .imm_ext  (imm_ext),
        .sel      (ALUSrc),
        .alu_in2  (alu_in2)
    );
    ula ALU (
        .op_a    (reg_rd1),
        .op_b    (alu_in2),
        .control (ALUControl),
        .result  (alu_res),
        .zero    (zero)
    );

    // Data Memory  
    wire [31:0] data_rd;
    data_mem DM (
        .clk        (clk),
        .MemRead    (MemRead),
        .MemWrite   (MemWrite),
        .addr       (alu_res[9:0]),
        .write_data (reg_rd2),
        .read_data  (data_rd)
    );

    // ** PC update **  
    assign pc_branch = PC + imm_ext;
    pc_mux M2 (
        .pc_plus4     (pc_plus4),
        .branch_target(pc_branch),
        .sel           (Branch & zero),
        .pc_next       (next_pc)
    );

    // PC register  
    always @(posedge clk) begin
        if (rst)
            PC <= 32'd0;
        else
            PC <= next_pc;
    end

    assign pc_out = PC;

endmodule

tb/datapath/datapath_tb.v
`timescale 1ns/1ps

module datapath_tb;
    reg        clk = 0;
    reg        rst = 1;
    wire [31:0] pc_out;

    data_path uut (
        .clk    (clk),
        .rst    (rst),
        .pc_out (pc_out)
    );

    always #5 clk = ~clk;

    initial begin
        $dumpfile("datapath_tb.vcd");
        $dumpvars(0, datapath_tb);

        #12 rst = 0;

        #200 $finish;
    end

    // cabeçalho do print
    initial begin
        $display("Time(ns)\tPC");
    end

    // a cada borda de subida do clock, depois do reset, imprime PC
    always @(posedge clk) begin
        if (!rst) begin
            $display("%0d\t\t%0d", $time, pc_out);
        end
    end

endmodule

tb/datapath/datapath_tb.vcd
$date
	Sun Jun 08 23:00:44 2025
$end
$version
	Icarus Verilog
$end
$timescale
	1ps
$end
$scope module datapath_tb $end
$var wire 32 ! pc_out [31:0] $end
$var reg 1 " clk $end
$var reg 1 # rst $end
$scope module uut $end
$var wire 1 " clk $end
$var wire 32 $ pc_out [31:0] $end
$var wire 1 # rst $end
$var wire 1 % zero $end
$var wire 5 & rs2 [4:0] $end
$var wire 5 ' rs1 [4:0] $end
$var wire 32 ( reg_rd2 [31:0] $end
$var wire 32 ) reg_rd1 [31:0] $end
$var wire 5 * rd [4:0] $end
$var wire 32 + pc_plus4 [31:0] $end
$var wire 32 , pc_branch [31:0] $end
$var wire 7 - opcode [6:0] $end
$var wire 32 . next_pc [31:0] $end
$var wire 32 / instr [31:0] $end
$var wire 2 0 imm_sel [1:0] $end
$var wire 32 1 imm_ext [31:0] $end
$var wire 1 2 funct7_5 $end
$var wire 3 3 funct3 [2:0] $end
$var wire 32 4 data_rd [31:0] $end
$var wire 32 5 alu_res [31:0] $end
$var wire 32 6 alu_in2 [31:0] $end
$var wire 1 7 RegWrite $end
$var wire 1 8 MemWrite $end
$var wire 1 9 MemToReg $end
$var wire 1 : MemRead $end
$var wire 1 ; Branch $end
$var wire 1 < ALUSrc $end
$var wire 2 = ALUControl [1:0] $end
$var reg 32 > PC [31:0] $end
$scope module ALU $end
$var wire 1 % zero $end
$var wire 32 ? op_b [31:0] $end
$var wire 32 @ op_a [31:0] $end
$var wire 2 A control [1:0] $end
$var reg 32 B result [31:0] $end
$upscope $end
$scope module CU $end
$var wire 3 C funct3 [2:0] $end
$var wire 1 2 funct7_5 $end
$var wire 7 D opcode [6:0] $end
$var reg 2 E ALUControl [1:0] $end
$var reg 1 < ALUSrc $end
$var reg 1 ; Branch $end
$var reg 1 : MemRead $end
$var reg 1 9 MemToReg $end
$var reg 1 8 MemWrite $end
$var reg 1 7 RegWrite $end
$upscope $end
$scope module DM $end
$var wire 1 : MemRead $end
$var wire 1 8 MemWrite $end
$var wire 10 F addr [9:0] $end
$var wire 1 " clk $end
$var wire 32 G write_data [31:0] $end
$var reg 32 H read_data [31:0] $end
$upscope $end
$scope module IG $end
$var wire 2 I sel [1:0] $end
$var wire 32 J instr [31:0] $end
$var wire 12 K imm_s [11:0] $end
$var wire 12 L imm_i [11:0] $end
$var wire 13 M imm_b [12:0] $end
$var reg 32 N imm_out [31:0] $end
$upscope $end
$scope module IM $end
$var wire 8 O addr [7:0] $end
$var reg 32 P instr [31:0] $end
$upscope $end
$scope module M1 $end
$var wire 32 Q imm_ext [31:0] $end
$var wire 1 < sel $end
$var wire 32 R reg_data2 [31:0] $end
$var reg 32 S alu_in2 [31:0] $end
$upscope $end
$scope module M2 $end
$var wire 32 T branch_target [31:0] $end
$var wire 32 U pc_plus4 [31:0] $end
$var wire 1 V sel $end
$var reg 32 W pc_next [31:0] $end
$upscope $end
$scope module RF $end
$var wire 1 7 RegWrite $end
$var wire 1 " clk $end
$var wire 5 X rd [4:0] $end
$var wire 5 Y rs1 [4:0] $end
$var wire 5 Z rs2 [4:0] $end
$var wire 32 [ write_data [31:0] $end
$var wire 32 \ read_data2 [31:0] $end
$var wire 32 ] read_data1 [31:0] $end
$var integer 32 ^ i [31:0] $end
$upscope $end
$upscope $end
$upscope $end
$enddefinitions $end
#0
$dumpvars
b100000 ^
bx ]
bx \
bx [
bx Z
bx Y
bx X
bx W
xV
bx U
bx T
bx S
bx R
b0 Q
bx P
bx O
b0 N
bx0 M
bx L
bx K
bx J
bx I
bx H
bx G
bx F
bx E
bx D
bx C
bx B
bx A
bx @
bx ?
bx >
bx =
x<
x;
x:
x9
x8
x7
bx 6
bx 5
bx 4
bx 3
x2
b0 1
bx 0
bx /
bx .
bx -
bx ,
bx +
bx *
bx )
bx (
bx '
bx &
x%
bx $
1#
0"
bx !
$end
#5000
b101 F
b101 [
0%
b101 5
b101 B
b101 6
b101 ?
b101 S
0V
b0 4
b0 H
b101 1
b101 N
b101 Q
b0 (
b0 G
b0 R
b0 \
b0 )
b0 @
b0 ]
b0 0
b0 I
b0 =
b0 A
b0 E
09
1<
0;
08
0:
17
b100000000000 M
b1 K
b101 L
02
b0 3
b0 C
b1 *
b1 X
b101 &
b101 Z
b0 '
b0 Y
b10011 -
b10011 D
b10100000000000010010011 /
b10100000000000010010011 J
b10100000000000010010011 P
b0 O
b100 .
b100 W
b100 +
b100 U
b101 ,
b101 T
b0 !
b0 $
b0 >
1"
#10000
0"
#12000
0#
#15000
b0 F
1%
b0 5
b0 B
bx [
bx 4
bx H
b0 6
b0 ?
b0 S
b0 1
b0 N
b0 Q
19
1:
1<
17
b10 M
b10 K
b0 L
b10 *
b10 X
b0 &
b0 Z
b10 '
b10 Y
b11 -
b11 D
b10000000100000011 /
b10000000100000011 J
b10000000100000011 P
b100 O
b1000 .
b1000 W
b1000 +
b1000 U
b100 ,
b100 T
b100 !
b100 $
b100 >
1"
#20000
0"
#25000
bx 6
bx ?
bx S
b0 4
b0 H
bx (
bx G
bx R
bx \
bx 0
bx I
09
0<
0:
07
bx F
bx0 M
bx K
bx L
x2
bx 3
bx C
bx *
bx X
bx &
bx Z
bx '
bx Y
bx -
bx D
x%
bx 5
bx B
bx /
bx J
bx P
bx )
bx @
bx ]
b1000 O
b1100 .
b1100 W
b1100 +
b1100 U
b1000 ,
b1000 T
b1000 !
b1000 $
b1000 >
1"
#30000
0"
#35000
b1100 O
b10000 .
b10000 W
b10000 +
b10000 U
b1100 ,
b1100 T
b1100 !
b1100 $
b1100 >
1"
#40000
0"
#45000
b10000 O
b10100 .
b10100 W
b10100 +
b10100 U
b10000 ,
b10000 T
b10000 !
b10000 $
b10000 >
1"
#50000
0"
#55000
b10100 O
b11000 .
b11000 W
b11000 +
b11000 U
b10100 ,
b10100 T
b10100 !
b10100 $
b10100 >
1"
#60000
0"
#65000
b11000 O
b11100 .
b11100 W
b11100 +
b11100 U
b11000 ,
b11000 T
b11000 !
b11000 $
b11000 >
1"
#70000
0"
#75000
b11100 O
b100000 .
b100000 W
b100000 +
b100000 U
b11100 ,
b11100 T
b11100 !
b11100 $
b11100 >
1"
#80000
0"
#85000
b100000 O
b100100 .
b100100 W
b100100 +
b100100 U
b100000 ,
b100000 T
b100000 !
b100000 $
b100000 >
1"
#90000
0"
#95000
b100100 O
b101000 .
b101000 W
b101000 +
b101000 U
b100100 ,
b100100 T
b100100 !
b100100 $
b100100 >
1"
#100000
0"
#105000
b101000 O
b101100 .
b101100 W
b101100 +
b101100 U
b101000 ,
b101000 T
b101000 !
b101000 $
b101000 >
1"
#110000
0"
#115000
b101100 O
b110000 .
b110000 W
b110000 +
b110000 U
b101100 ,
b101100 T
b101100 !
b101100 $
b101100 >
1"
#120000
0"
#125000
b110000 O
b110100 .
b110100 W
b110100 +
b110100 U
b110000 ,
b110000 T
b110000 !
b110000 $
b110000 >
1"
#130000
0"
#135000
b110100 O
b111000 .
b111000 W
b111000 +
b111000 U
b110100 ,
b110100 T
b110100 !
b110100 $
b110100 >
1"
#140000
0"
#145000
b111000 O
b111100 .
b111100 W
b111100 +
b111100 U
b111000 ,
b111000 T
b111000 !
b111000 $
b111000 >
1"
#150000
0"
#155000
b111100 O
b1000000 .
b1000000 W
b1000000 +
b1000000 U
b111100 ,
b111100 T
b111100 !
b111100 $
b111100 >
1"
#160000
0"
#165000
b1000000 O
b1000100 .
b1000100 W
b1000100 +
b1000100 U
b1000000 ,
b1000000 T
b1000000 !
b1000000 $
b1000000 >
1"
#170000
0"
#175000
b1000100 O
b1001000 .
b1001000 W
b1001000 +
b1001000 U
b1000100 ,
b1000100 T
b1000100 !
b1000100 $
b1000100 >
1"
#180000
0"
#185000
b1001000 O
b1001100 .
b1001100 W
b1001100 +
b1001100 U
b1001000 ,
b1001000 T
b1001000 !
b1001000 $
b1001000 >
1"
#190000
0"
#195000
b1001100 O
b1010000 .
b1010000 W
b1010000 +
b1010000 U
b1001100 ,
b1001100 T
b1001100 !
b1001100 $
b1001100 >
1"
#200000
0"
#205000
b1010000 O
b1010100 .
b1010100 W
b1010100 +
b1010100 U
b1010000 ,
b1010000 T
b1010000 !
b1010000 $
b1010000 >
1"
